openapi_client/__init__.py
openapi_client/api_client.py
openapi_client/configuration.py
openapi_client/exceptions.py
openapi_client/model_utils.py
openapi_client/rest.py
openapi_client/api/__init__.py
openapi_client/api/conversions_api.py
openapi_client/api/open_wardley_maps_api.py
openapi_client/api/tools_api.py
openapi_client/api/wardley_maps_online_api.py
openapi_client/apis/__init__.py
openapi_client/model/__init__.py
openapi_client/model/component_request.py
openapi_client/model/http_validation_error.py
openapi_client/model/map_id_request.py
openapi_client/model/map_text_and_warnings.py
openapi_client/model/owm_text_request.py
openapi_client/model/search_component_request.py
openapi_client/model/text_request.py
openapi_client/model/validation_error.py
openapi_client/models/__init__.py
WardleyMapsCrew_API_Python_SDK-0.5.0.dist-info/METADATA
WardleyMapsCrew_API_Python_SDK-0.5.0.dist-info/WHEEL
WardleyMapsCrew_API_Python_SDK-0.5.0.dist-info/top_level.txt
WardleyMapsCrew_API_Python_SDK-0.5.0.dist-info/RECORD
