Metadata-Version: 2.1
Name: WardleyMapsCrew-API-Python-SDK
Version: 0.5.0
Summary: Wardley Mapping Crew API
Home-page: 
Author: OpenAPI Generator community
Author-email: team@openapitools.org
Keywords: OpenAPI,OpenAPI-Generator,Wardley Mapping Crew API
Requires-Python: >=3.6
Requires-Dist: urllib3 >=1.25.3
Requires-Dist: python-dateutil
